CHANGELOG.txt
LICENSE.txt
MANIFEST.in
README.rst
setup.cfg
setup.py
bin/__init__.py
bin/ebird-convert
data/birdlife_species_names.csv
docs/ebird-convert.rst
ebird_import/__init__.py
ebird_import/handlers.py
ebird_import/shared.py
ebird_import.egg-info/PKG-INFO
ebird_import.egg-info/SOURCES.txt
ebird_import.egg-info/dependency_links.txt
ebird_import.egg-info/requires.txt
ebird_import.egg-info/top_level.txt
tests/__init__.py
tests/ebird_convert/__init__.py
tests/ebird_convert/test_convert_species.py
tests/ebird_convert/test_load_species.py
tests/ebird_convert/test_read_csv_file.py
tests/ebird_convert/test_read_header.py
tests/ebird_convert/test_resources.py