Metadata-Version: 1.1
Name: ebird-import
Version: 0.3.0
Summary: Tools for loading records into eBird
Home-page: http://pypi.python.org/pypi/ebird-import/
Author: Stuart MacKay
Author-email: smackay@flagstonesoftware.com
License: GPL
Keywords: eBird import csv
Platform: UNKNOWN
Classifier: Development Status :: 3 - Alpha
Classifier: Environment :: Console
Classifier: Intended Audience :: Science/Research
Classifier: License :: OSI Approved :: GNU General Public License v3 (GPLv3)
Classifier: Operating System :: OS Independent
Classifier: Programming Language :: Python
Classifier: Natural Language :: English
Classifier: Topic :: Text Processing :: Filters
